tdbuild/__init__.py
tdbuild/__main__.py
tdbuild/builder.py
tdbuild/cli.py
tdbuild/constants.py
tdbuild/template.py
tdbuild/utils.py
tdbuild/version.py
tdbuild/windows.py
tdbuild-3.0.6.dist-info/entry_points.txt
tdbuild-3.0.6.dist-info/WHEEL
tdbuild-3.0.6.dist-info/METADATA
tdbuild-3.0.6.dist-info/RECORD
