Metadata-Version: 2.1
Name: tdbuild
Version: 3.0.6
Summary: A simple build tool for C and C++
Home-page: https://spader.zone
Author: spader
Author-email: thomas.spader@gmail.com
Requires-Python: >=3.9,<4.0
Classifier: Programming Language :: Python :: 3
Classifier: Programming Language :: Python :: 3.9
Classifier: Programming Language :: Python :: 3.10
Requires-Dist: colorama (>=0.4.5,<0.5.0)
Project-URL: Repository, https://github.com/spaderthomas/tdbuild
